influx_prompt/__init__.py
influx_prompt/compat.py
influx_prompt/completer.py
influx_prompt/completion.py
influx_prompt/extra_command.py
influx_prompt/influx_client.py
influx_prompt/main.py
influx_prompt/tabular.py
influx_prompt-1.0.2.dist-info/LICENSE
influx_prompt-1.0.2.dist-info/METADATA
influx_prompt-1.0.2.dist-info/WHEEL
influx_prompt-1.0.2.dist-info/entry_points.txt
influx_prompt-1.0.2.dist-info/top_level.txt
influx_prompt-1.0.2.dist-info/RECORD
