Metadata-Version: 2.1
Name: influx-prompt
Version: 1.0.2
Summary: An interactive command-line influxdb cli with auto completion.
Home-page: https://github.com/RPing/influx-prompt
Author: Stephen Chen (RPing)
Author-email: g1222888@gmail.com
License: MIT
Keywords: influx influxdb cli
Platform: UNKNOWN
Classifier: Development Status :: 4 - Beta
Classifier: Environment :: Console
Classifier: Intended Audience :: Developers
Classifier: Topic :: Terminals
Classifier: Topic :: Text Processing
Classifier: Topic :: Utilities
Classifier: Programming Language :: Python :: 3.6
Classifier: Programming Language :: Python :: 3.7
Classifier: Programming Language :: Python :: 3.8
Classifier: Programming Language :: Python :: 3.9
Requires-Dist: requests (~=2.24)
Requires-Dist: prompt-toolkit (~=3.0)
Requires-Dist: jsane (~=0.1)
Requires-Dist: fuzzyfinder (~=2.1)
Requires-Dist: pygments (~=2.7)
